auth/__init__.py
auth/authenticate.py
issues/__init__.py
issues/get_issues.py
milestone/__init__.py
milestone/get_milestone.py
project/__init__.py
project/getProjectBySlug.py
tasks/__init__.py
tasks/get_task_history.py
tasks/get_tasks.py
test/__init__.py
test/test_getIssues.py
test/test_getProjectBySlug.py
test/test_get_milestone.py
test/test_get_task_history.py
test/test_get_tasks.py
userStory/__init__.py
userStory/getBusinessValue.py
userStory/get_user_story_history.py
hmtaiga-0.1.12.dist-info/METADATA
hmtaiga-0.1.12.dist-info/WHEEL
hmtaiga-0.1.12.dist-info/top_level.txt
hmtaiga-0.1.12.dist-info/RECORD
