Metadata-Version: 2.1
Name: hmtaiga
Version: 0.1.12
Summary: Taiga Library
Home-page: UNKNOWN
Author: shikhaverma
License: UNKNOWN
Platform: UNKNOWN
